{"total":3,"page":1,"size":null,"sortField":"id","sortDirection":"asc","result":[{"id":544,"version":0,"retailerId":"ee0c75dc","createdDate":1459376583000,"createdByUser":"","modifiedDate":null,"modifiedByUser":null,"physicalInventoryId":62,"itemId":306,"itemNumber":3,"itemColor":"Black","itemColor2":null,"itemSize":"0,2","quantity":3,"itemName":"Vintage Dress"},{"id":546,"version":0,"retailerId":"ee0c75dc","createdDate":1459376591000,"createdByUser":"","modifiedDate":null,"modifiedByUser":null,"physicalInventoryId":62,"itemId":307,"itemNumber":4,"itemColor":"Blue","itemColor2":null,"itemSize":"0,2","quantity":2,"itemName":"Vintage Dress"},{"id":547,"version":0,"retailerId":"ee0c75dc","createdDate":1459376593000,"createdByUser":"","modifiedDate":null,"modifiedByUser":null,"physicalInventoryId":62,"itemId":308,"itemNumber":5,"itemColor":"Red","itemColor2":null,"itemSize":"4","quantity":1,"itemName":"Chest-Crossed Dress"}]}